{
  "timeframe": "1m",
  "timestamp": "2025-04-04T07:29:36.677169Z",
  "predictions": [
    {
      "symbol": "BTC/USDT",
      "decision": "SELL",
      "confidence": 0.8276,
      "price": 83631.17
    },
    {
      "symbol": "BNB/USDT",
      "decision": "SELL",
      "confidence": 0.6404,
      "price": 597.4
    },
    {
      "symbol": "NEO/USDT",
      "decision": "BUY",
      "confidence": 0.6343,
      "price": 4.74
    },
    {
      "symbol": "LINK/USDT",
      "decision": "SELL",
      "confidence": 0.6245,
      "price": 13.0
    },
    {
      "symbol": "TRX/USDT",
      "decision": "SELL",
      "confidence": 0.7407,
      "price": 0.2386
    },
    {
      "symbol": "XRP/USDT",
      "decision": "BUY",
      "confidence": 0.6982,
      "price": 2.0729
    },
    {
      "symbol": "VET/USDT",
      "decision": "BUY",
      "confidence": 0.8227,
      "price": 0.02204
    },
    {
      "symbol": "ADA/USDT",
      "decision": "BUY",
      "confidence": 0.7069,
      "price": 0.6604
    },
    {
      "symbol": "LTC/USDT",
      "decision": "SELL",
      "confidence": 0.5028,
      "price": 84.46
    },
    {
      "symbol": "ETC/USDT",
      "decision": "SELL",
      "confidence": 0.6078,
      "price": 16.36
    },
    {
      "symbol": "ETH/USDT",
      "decision": "BUY",
      "confidence": 0.5812,
      "price": 1814.84
    },
    {
      "symbol": "IOTA/USDT",
      "decision": "BUY",
      "confidence": 0.6334,
      "price": 0.1672
    },
    {
      "symbol": "EOS/USDT",
      "decision": "SELL",
      "confidence": 0.9187,
      "price": 0.8357
    },
    {
      "symbol": "USDC/USDT",
      "decision": "SELL",
      "confidence": 0.968,
      "price": 1.0002
    },
    {
      "symbol": "XLM/USDT",
      "decision": "SELL",
      "confidence": 0.5281,
      "price": 0.2616
    },
    {
      "symbol": "FET/USDT",
      "decision": "SELL",
      "confidence": 0.6329,
      "price": 0.44
    },
    {
      "symbol": "EUR/USDT",
      "decision": "BUY",
      "confidence": 0.5709,
      "price": 1.1049
    },
    {
      "symbol": "ATOM/USDT",
      "decision": "SELL",
      "confidence": 0.571,
      "price": 4.817
    },
    {
      "symbol": "FUN/USDT",
      "decision": "SELL",
      "confidence": 0.8877,
      "price": 0.005302
    },
    {
      "symbol": "NKN/USDT",
      "decision": "BUY",
      "confidence": 0.7014,
      "price": 0.0267
    },
    {
      "symbol": "DOGE/USDT",
      "decision": "BUY",
      "confidence": 0.5009,
      "price": 0.16542
    },
    {
      "symbol": "SOL/USDT",
      "decision": "BUY",
      "confidence": 0.8132,
      "price": 117.43
    },
    {
      "symbol": "ALGO/USDT",
      "decision": "SELL",
      "confidence": 0.5871,
      "price": 0.184
    },
    {
      "symbol": "BCH/USDT",
      "decision": "SELL",
      "confidence": 0.5115,
      "price": 308.5
    },
    {
      "symbol": "HBAR/USDT",
      "decision": "SELL",
      "confidence": 0.903,
      "price": 0.16344
    },
    {
      "symbol": "COMP/USDT",
      "decision": "BUY",
      "confidence": 0.6419,
      "price": 45.29
    },
    {
      "symbol": "CRV/USDT",
      "decision": "SELL",
      "confidence": 0.5116,
      "price": 0.5251
    },
    {
      "symbol": "DGB/USDT",
      "decision": "SELL",
      "confidence": 0.8541,
      "price": 0.01102
    },
    {
      "symbol": "MKR/USDT",
      "decision": "BUY",
      "confidence": 0.9016,
      "price": 1317.0
    },
    {
      "symbol": "DOT/USDT",
      "decision": "SELL",
      "confidence": 0.7306,
      "price": 4.075
    },
    {
      "symbol": "RSR/USDT",
      "decision": "SELL",
      "confidence": 0.5177,
      "price": 0.006718
    },
    {
      "symbol": "PAXG/USDT",
      "decision": "SELL",
      "confidence": 0.5692,
      "price": 3112.0
    },
    {
      "symbol": "EGLD/USDT",
      "decision": "SELL",
      "confidence": 0.7433,
      "price": 15.25
    },
    {
      "symbol": "AVAX/USDT",
      "decision": "SELL",
      "confidence": 0.7377,
      "price": 18.54
    },
    {
      "symbol": "RUNE/USDT",
      "decision": "SELL",
      "confidence": 0.7434,
      "price": 1.135
    },
    {
      "symbol": "NEAR/USDT",
      "decision": "SELL",
      "confidence": 0.7733,
      "price": 2.538
    },
    {
      "symbol": "FIL/USDT",
      "decision": "SELL",
      "confidence": 0.6353,
      "price": 2.958
    },
    {
      "symbol": "AAVE/USDT",
      "decision": "BUY",
      "confidence": 0.8466,
      "price": 151.68
    },
    {
      "symbol": "UNI/USDT",
      "decision": "SELL",
      "confidence": 0.8257,
      "price": 5.974
    },
    {
      "symbol": "WING/USDT",
      "decision": "SELL",
      "confidence": 0.644,
      "price": 1.884
    },
    {
      "symbol": "INJ/USDT",
      "decision": "SELL",
      "confidence": 0.5185,
      "price": 8.52
    },
    {
      "symbol": "CAKE/USDT",
      "decision": "SELL",
      "confidence": 0.8007,
      "price": 1.828
    },
    {
      "symbol": "PERP/USDT",
      "decision": "SELL",
      "confidence": 0.5181,
      "price": 0.2381
    },
    {
      "symbol": "OM/USDT",
      "decision": "SELL",
      "confidence": 0.5244,
      "price": 6.3375
    },
    {
      "symbol": "CFX/USDT",
      "decision": "BUY",
      "confidence": 0.5952,
      "price": 0.0814
    },
    {
      "symbol": "BURGER/USDT",
      "decision": "BUY",
      "confidence": 0.8078,
      "price": 0.0172
    },
    {
      "symbol": "SHIB/USDT",
      "decision": "BUY",
      "confidence": 0.5997,
      "price": 1.229e-05
    },
    {
      "symbol": "ICP/USDT",
      "decision": "SELL",
      "confidence": 0.8124,
      "price": 5.208
    },
    {
      "symbol": "GALA/USDT",
      "decision": "SELL",
      "confidence": 0.7267,
      "price": 0.01523
    },
    {
      "symbol": "MASK/USDT",
      "decision": "BUY",
      "confidence": 0.6119,
      "price": 1.187
    },
    {
      "symbol": "MLN/USDT",
      "decision": "SELL",
      "confidence": 0.7616,
      "price": 10.19
    },
    {
      "symbol": "RAY/USDT",
      "decision": "SELL",
      "confidence": 0.9527,
      "price": 1.807
    },
    {
      "symbol": "DYDX/USDT",
      "decision": "BUY",
      "confidence": 0.7513,
      "price": 0.6216
    },
    {
      "symbol": "MBOX/USDT",
      "decision": "BUY",
      "confidence": 0.9435,
      "price": 0.0529
    },
    {
      "symbol": "RARE/USDT",
      "decision": "SELL",
      "confidence": 0.6511,
      "price": 0.0771
    },
    {
      "symbol": "AUCTION/USDT",
      "decision": "BUY",
      "confidence": 0.5922,
      "price": 13.16
    },
    {
      "symbol": "AMP/USDT",
      "decision": "BUY",
      "confidence": 0.9058,
      "price": 0.003654
    },
    {
      "symbol": "BNX/USDT",
      "decision": "SELL",
      "confidence": 0.6449,
      "price": 1.7819
    },
    {
      "symbol": "LINA/USDT",
      "decision": "BUY",
      "confidence": 0.7684,
      "price": 0.000337
    },
    {
      "symbol": "VOXEL/USDT",
      "decision": "SELL",
      "confidence": 0.7366,
      "price": 0.0375
    },
    {
      "symbol": "ACH/USDT",
      "decision": "BUY",
      "confidence": 0.6089,
      "price": 0.0212
    },
    {
      "symbol": "IMX/USDT",
      "decision": "BUY",
      "confidence": 0.58,
      "price": 0.462
    },
    {
      "symbol": "API3/USDT",
      "decision": "SELL",
      "confidence": 0.5347,
      "price": 0.878
    },
    {
      "symbol": "GMT/USDT",
      "decision": "BUY",
      "confidence": 0.7925,
      "price": 0.0457
    },
    {
      "symbol": "LDO/USDT",
      "decision": "SELL",
      "confidence": 0.7039,
      "price": 0.849
    },
    {
      "symbol": "OP/USDT",
      "decision": "BUY",
      "confidence": 0.8223,
      "price": 0.713
    },
    {
      "symbol": "ARB/USDT",
      "decision": "BUY",
      "confidence": 0.5097,
      "price": 0.316
    },
    {
      "symbol": "APT/USDT",
      "decision": "BUY",
      "confidence": 0.8541,
      "price": 5.056
    },
    {
      "symbol": "BSW/USDT",
      "decision": "BUY",
      "confidence": 0.5946,
      "price": 0.018
    },
    {
      "symbol": "WBTC/USDT",
      "decision": "SELL",
      "confidence": 0.8271,
      "price": 83544.89
    },
    {
      "symbol": "SUI/USDT",
      "decision": "SELL",
      "confidence": 0.8656,
      "price": 2.2432
    },
    {
      "symbol": "PEPE/USDT",
      "decision": "BUY",
      "confidence": 0.7237,
      "price": 7e-06
    },
    {
      "symbol": "FLOKI/USDT",
      "decision": "BUY",
      "confidence": 0.837,
      "price": 5.589e-05
    },
    {
      "symbol": "COMBO/USDT",
      "decision": "BUY",
      "confidence": 0.9371,
      "price": 0.0276
    },
    {
      "symbol": "PENDLE/USDT",
      "decision": "SELL",
      "confidence": 0.777,
      "price": 3.179
    },
    {
      "symbol": "ARKM/USDT",
      "decision": "BUY",
      "confidence": 0.9009,
      "price": 0.501
    },
    {
      "symbol": "WLD/USDT",
      "decision": "BUY",
      "confidence": 0.7795,
      "price": 0.765
    },
    {
      "symbol": "FDUSD/USDT",
      "decision": "SELL",
      "confidence": 0.6864,
      "price": 0.9971
    },
    {
      "symbol": "SEI/USDT",
      "decision": "SELL",
      "confidence": 0.8496,
      "price": 0.1641
    },
    {
      "symbol": "JTO/USDT",
      "decision": "SELL",
      "confidence": 0.6379,
      "price": 1.976
    },
    {
      "symbol": "TIA/USDT",
      "decision": "SELL",
      "confidence": 0.6947,
      "price": 2.838
    },
    {
      "symbol": "JUP/USDT",
      "decision": "SELL",
      "confidence": 0.5498,
      "price": 0.3973
    },
    {
      "symbol": "BONK/USDT",
      "decision": "SELL",
      "confidence": 0.9013,
      "price": 1.119e-05
    },
    {
      "symbol": "1000SATS/USDT",
      "decision": "BUY",
      "confidence": 0.9137,
      "price": 5.34e-05
    },
    {
      "symbol": "ORDI/USDT",
      "decision": "SELL",
      "confidence": 0.9026,
      "price": 7.34
    },
    {
      "symbol": "VANRY/USDT",
      "decision": "SELL",
      "confidence": 0.647,
      "price": 0.0258
    },
    {
      "symbol": "STRK/USDT",
      "decision": "BUY",
      "confidence": 0.6518,
      "price": 0.1373
    },
    {
      "symbol": "WIF/USDT",
      "decision": "SELL",
      "confidence": 0.7382,
      "price": 0.383
    },
    {
      "symbol": "ENA/USDT",
      "decision": "BUY",
      "confidence": 0.7416,
      "price": 0.3198
    },
    {
      "symbol": "W/USDT",
      "decision": "SELL",
      "confidence": 0.8869,
      "price": 0.0868
    },
    {
      "symbol": "REZ/USDT",
      "decision": "BUY",
      "confidence": 0.7123,
      "price": 0.01728
    },
    {
      "symbol": "TAO/USDT",
      "decision": "BUY",
      "confidence": 0.56,
      "price": 218.1
    },
    {
      "symbol": "IO/USDT",
      "decision": "SELL",
      "confidence": 0.5514,
      "price": 0.644
    },
    {
      "symbol": "ZRO/USDT",
      "decision": "BUY",
      "confidence": 0.5084,
      "price": 2.997
    },
    {
      "symbol": "RENDER/USDT",
      "decision": "SELL",
      "confidence": 0.6422,
      "price": 3.284
    },
    {
      "symbol": "POL/USDT",
      "decision": "BUY",
      "confidence": 0.7251,
      "price": 0.1901
    },
    {
      "symbol": "NEIRO/USDT",
      "decision": "BUY",
      "confidence": 0.6581,
      "price": 0.00017844
    },
    {
      "symbol": "TON/USDT",
      "decision": "SELL",
      "confidence": 0.5856,
      "price": 3.532
    },
    {
      "symbol": "ETHFI/USDT",
      "decision": "SELL",
      "confidence": 0.6743,
      "price": 0.523
    }
  ]
}